PySAGA_cmd/__init__.py
PySAGA_cmd/objects.py
PySAGA_cmd/saga.py
PySAGA_cmd/utils.py
PySAGA_cmd/assets/DEM_30m.tif
PySAGA_cmd/tests/__init__.py
PySAGA_cmd/tests/test_saga.py
PySAGA_cmd/tests/test_utils.py
PySAGA_cmd-1.2.6.dist-info/LICENSE
PySAGA_cmd-1.2.6.dist-info/METADATA
PySAGA_cmd-1.2.6.dist-info/WHEEL
PySAGA_cmd-1.2.6.dist-info/top_level.txt
PySAGA_cmd-1.2.6.dist-info/RECORD
