Metadata-Version: 2.1
Name: PySAGA-cmd
Version: 1.2.6
Summary: A package that allows you to run SAGA GIS tools using Python.
Author-email: Alex-Andrei Cuvuliuc <cuvuliucalexandrei@gmail.com>
License: MIT
Project-URL: Homepage, https://github.com/alecsandrei/PySAGA-cmd
Keywords: PySAGA-cmd
Classifier: Intended Audience :: Developers
Classifier: License :: OSI Approved :: MIT License
Classifier: Natural Language :: English
Classifier: Programming Language :: Python :: 3.9
Classifier: Programming Language :: Python :: 3.10
Classifier: Programming Language :: Python :: 3.11
Classifier: Programming Language :: Python :: 3.12
Requires-Python: >=3.9
License-File: LICENSE
Provides-Extra: all
Requires-Dist: PySAGA-cmd[dev,extras] ; extra == 'all'
Provides-Extra: dev
Requires-Dist: twine ; extra == 'dev'
Requires-Dist: zest.releaser[recommended] ; extra == 'dev'
Requires-Dist: mypy ; extra == 'dev'
Requires-Dist: flake8 ; extra == 'dev'
Requires-Dist: Flake8-pyproject ; extra == 'dev'
Requires-Dist: pytest ; extra == 'dev'
Provides-Extra: extras
Requires-Dist: numpy ; extra == 'extras'
Requires-Dist: matplotlib ; extra == 'extras'
Requires-Dist: rasterio ; extra == 'extras'
Requires-Dist: geopandas ; extra == 'extras'
Requires-Dist: pyogrio ; extra == 'extras'
Requires-Dist: xarray ; extra == 'extras'
Requires-Dist: rioxarray ; extra == 'extras'
